documentcloud/__init__.py
documentcloud/addon.py
documentcloud/annotations.py
documentcloud/base.py
documentcloud/client.py
documentcloud/constants.py
documentcloud/documents.py
documentcloud/exceptions.py
documentcloud/organizations.py
documentcloud/projects.py
documentcloud/sections.py
documentcloud/toolbox.py
documentcloud/users.py
documentcloud-3.0.0.dist-info/LICENSE
documentcloud-3.0.0.dist-info/METADATA
documentcloud-3.0.0.dist-info/WHEEL
documentcloud-3.0.0.dist-info/top_level.txt
documentcloud-3.0.0.dist-info/RECORD
